bkheatmap.py
bkheatmap-0.1.5.dist-info/DESCRIPTION.rst
bkheatmap-0.1.5.dist-info/METADATA
bkheatmap-0.1.5.dist-info/RECORD
bkheatmap-0.1.5.dist-info/WHEEL
bkheatmap-0.1.5.dist-info/entry_points.txt
bkheatmap-0.1.5.dist-info/metadata.json
bkheatmap-0.1.5.dist-info/top_level.txt
