Metadata-Version: 2.0
Name: bkheatmap
Version: 0.1.5
Summary: A Bokeh heatmap for Python
Home-page: https://github.com/wwliao/bkheatmap
Author: Wen-Wei Liao
Author-email: gattacaliao@gmail.com
License: GPLv3
Keywords: Bokeh heatmap
Platform: UNKNOWN
Classifier: Development Status :: 3 - Alpha
Classifier: Environment :: Console
Classifier: Intended Audience :: Science/Research
Classifier: License :: OSI Approved :: GNU General Public License v3 (GPLv3)
Classifier: Natural Language :: English
Classifier: Operating System :: MacOS :: MacOS X
Classifier: Operating System :: POSIX :: Linux
Classifier: Operating System :: Unix
Classifier: Programming Language :: Python :: 2.7
Classifier: Topic :: Scientific/Engineering :: Visualization
Requires-Dist: bokeh
Requires-Dist: matplotlib
Requires-Dist: numpy
Requires-Dist: pandas
Requires-Dist: scipy
